aser/__init__.py
aser/a2aser.py
aser/agent.py
aser/api.py
aser/cli.py
aser/cot.py
aser/evaluator.py
aser/knowledge.py
aser/mcp.py
aser/memory.py
aser/team.py
aser/text2sql.py
aser/tools.py
aser/trace.py
aser/workflow.py
aser/connectors/__init__.py
aser/connectors/seika.py
aser/connectors/abi/seika_abi.json
aser/social/__init__.py
aser/social/bluesky.py
aser/social/discord.py
aser/social/farcaster.py
aser/social/mastodon.py
aser/social/telegram.py
aser/social/twitter.py
aser/storage/__init__.py
aser/storage/sqlite.py
aser/storage/supabase.py
aser/storage/tinydb.py
aser/toolkits/__init__.py
aser/toolkits/blockbeats.py
aser/toolkits/cast.py
aser/toolkits/cogview3.py
aser/toolkits/coinmarketcap.py
aser/toolkits/deepgram.py
aser/toolkits/defillama.py
aser/toolkits/erc20.py
aser/toolkits/exa.py
aser/toolkits/giphy.py
aser/toolkits/goplus.py
aser/toolkits/pancake.py
aser/toolkits/runware.py
aser/toolkits/v2ex.py
aser/toolkits/web3bio.py
aser/utils/__init__.py
aser/utils/erc8004_extension.py
aser/utils/get_chunks.py
aser/utils/get_file_data.py
aser/utils/get_function_parameters.py
aser/utils/handle_tool_function.py
aser/utils/knowledge_to_prompt.py
aser/utils/safe_serialize.py
aser-0.1.9.dist-info/METADATA
aser-0.1.9.dist-info/WHEEL
aser-0.1.9.dist-info/top_level.txt
aser-0.1.9.dist-info/RECORD
