Metadata-Version: 2.4
Name: aser
Version: 0.1.9
Summary: An AI Agent
Author-email: rickey <hello_rickey@163.com>
License: MIT
Project-URL: Homepage, https://github.com/AmeNetwork/aser
Project-URL: Bug Tracker, https://github.com/AmeNetwork/aser/issues
Classifier: Programming Language :: Python :: 3
Classifier: License :: OSI Approved :: MIT License
Classifier: Operating System :: OS Independent
Requires-Python: >=3.13.2
Requires-Dist: openai>=1.63.2
Requires-Dist: web3>=7.8.0
Requires-Dist: discord-py-interactions>=5.14.0
Requires-Dist: python-telegram-bot>=21.10
Requires-Dist: tweepy>=4.15.0
Requires-Dist: supabase>=2.13.0
Requires-Dist: tinydb>=4.8.2
Requires-Dist: fastapi>=0.115.8
Requires-Dist: uvicorn>=0.34.0
Requires-Dist: python-dotenv>=1.0.1
Requires-Dist: chromadb>=0.6.3
Requires-Dist: tiktoken>=0.9.0
Requires-Dist: canonicaljson>=2.0.0
Requires-Dist: mastodon.py>=2.0.1
Requires-Dist: atproto>=0.0.59
Requires-Dist: rich>=13.9.4
Requires-Dist: semchunk>=3.2.3
Requires-Dist: fastmcp>=2.12.3
Requires-Dist: mscp>=0.1.4
Requires-Dist: a2a-sdk>=0.3.6
